carta/__init__.py
carta/carta.py
carta/carta_final.py
carta/carta_main.py
carta/fastCarta.py
carta/ilp.py
carta/utils.py
carta/.ipynb_checkpoints/run_ice_fase-checkpoint.R
carta_cell-1.0.1.dist-info/METADATA
carta_cell-1.0.1.dist-info/WHEEL
carta_cell-1.0.1.dist-info/entry_points.txt
carta_cell-1.0.1.dist-info/licenses/LICENSE
carta_cell-1.0.1.dist-info/RECORD
