Metadata-Version: 2.4
Name: carta-cell
Version: 1.0.1
Summary: Python package for cell differentiation mapping
Project-URL: Homepage, https://github.com/raphael-group/CARTA
Project-URL: Issues, https://github.com/raphael-group/CARTA/issues
Author-email: Palash Sashittal and Richard Zhang <sashittal@vt.edu>
License: MIT License
License-File: LICENSE
Classifier: License :: OSI Approved :: MIT License
Classifier: Operating System :: Microsoft :: Windows
Classifier: Operating System :: OS Independent
Classifier: Operating System :: POSIX :: Linux
Classifier: Programming Language :: Python :: 3
Classifier: Topic :: Scientific/Engineering :: Bio-Informatics
Requires-Python: ==3.10.13
Requires-Dist: ete3
Requires-Dist: gurobipy==11.0.0
Requires-Dist: loguru
Requires-Dist: networkx
Requires-Dist: numpy
Requires-Dist: pandas==2.2.3
